README.md
setup.py
motorparts/__init__.py
motorparts.egg-info/PKG-INFO
motorparts.egg-info/SOURCES.txt
motorparts.egg-info/dependency_links.txt
motorparts.egg-info/requires.txt
motorparts.egg-info/top_level.txt